cyclopy/__init__.py
cyclopy/cc.py
cyclopy-1.1.dist-info/entry_points.txt
cyclopy-1.1.dist-info/WHEEL
cyclopy-1.1.dist-info/METADATA
cyclopy-1.1.dist-info/RECORD
