Metadata-Version: 2.1
Name: cyclopy
Version: 1.1
Summary: A tool for calculating the cyclomatic complexity of projects written in python
Home-page: https://github.com/Split174/cyclopy
License: MIT
Author: Sergey Popov
Author-email: sergei.popov174@gmail.com
Requires-Python: >=3.5,<4.0
Classifier: License :: OSI Approved :: MIT License
Classifier: Programming Language :: Python :: 3
Classifier: Programming Language :: Python :: 3.5
Classifier: Programming Language :: Python :: 3.6
Classifier: Programming Language :: Python :: 3.7
Classifier: Programming Language :: Python :: 3.8
Requires-Dist: GitPython (>=3.1.12,<4.0.0)
Project-URL: Repository, https://github.com/Split174/cyclopy
